jianmu/__init__.py
jianmu/__main__.py
jianmu/action.py
jianmu/datatypes.py
jianmu/definitions.py
jianmu/exceptions.py
jianmu/info.py
jianmu/jm.py
jianmu/sock.py
jianmu/utils.py
jianmu/cli/__init__.py
jianmu/cli/build.py
jianmu/cli/clean.py
jianmu/cli/create.py
jianmu/cli/dev.py
jianmu/cli/start.py
jianmu/cli/upgrade.py
Jianmu-0.0.12.dist-info/LICENSE
Jianmu-0.0.12.dist-info/METADATA
Jianmu-0.0.12.dist-info/WHEEL
Jianmu-0.0.12.dist-info/entry_points.txt
Jianmu-0.0.12.dist-info/top_level.txt
Jianmu-0.0.12.dist-info/RECORD
