Metadata-Version: 2.1
Name: Jianmu
Version: 0.0.12
Summary: A simple desktop app development framework combining Python, Vue.js, Element Plus and Electron.
Home-page: https://github.com/frederick-wang/jianmu
Author: Zhaoji Wang
Author-email: hwoam@outlook.com
Project-URL: Bug Tracker, https://github.com/frederick-wang/jianmu/issues
Classifier: Operating System :: OS Independent
Classifier: Development Status :: 2 - Pre-Alpha
Classifier: Environment :: Console
Classifier: Environment :: MacOS X
Classifier: Environment :: Win32 (MS Windows)
Classifier: License :: OSI Approved :: Apache Software License
Classifier: Programming Language :: Python :: 3
Classifier: Programming Language :: Python :: 3.7
Classifier: Programming Language :: Python :: 3.8
Classifier: Programming Language :: Python :: 3.9
Classifier: Programming Language :: Python :: 3.10
Classifier: Programming Language :: Python :: 3.11
Requires-Python: >=3.7
License-File: LICENSE
Requires-Dist: dataclasses
Requires-Dist: Flask
Requires-Dist: flask-socketio
Requires-Dist: gevent
Requires-Dist: gevent-websocket
Requires-Dist: requests
Requires-Dist: rich
Requires-Dist: pyreactivity
Requires-Dist: typing-extensions
